Metadata-Version: 2.1
Name: django_events_sourcing
Version: 0.8.0
Summary: A Django app to dispatch events when model Create/Update and Delete operations are made.
Home-page: https://github.com/Mendes11/django_events_sourcing
Author: Rafael Mendes Pacini Bachiega
Author-email: rafaelmpb11@hotmail.com
License: Apache 2.0
Classifier: Environment :: Web Environment
Classifier: Framework :: Django
Classifier: Framework :: Django :: 2.2
Classifier: Intended Audience :: Developers
Classifier: Operating System :: OS Independent
Classifier: Programming Language :: Python
Classifier: Programming Language :: Python :: 3
Classifier: Programming Language :: Python :: 3 :: Only
Classifier: Programming Language :: Python :: 3.6
Classifier: Programming Language :: Python :: 3.7
Classifier: Programming Language :: Python :: 3.8
Classifier: Topic :: Internet :: WWW/HTTP
Classifier: Topic :: Internet :: WWW/HTTP :: Dynamic Content
License-File: LICENSE
